src/__init__.py
src/whisperyt/__init__.py
src/whisperyt/main.py
src/whisperyt/postprocess.py
src/whisperyt/transcribe.py
whisperyt/__init__.py
whisperyt/postprocess.py
whisperyt/prerecorded.py
whisperyt/stream.py
whisperyt/transcribe.py
whisperyt-0.1.4.dist-info/LICENSE
whisperyt-0.1.4.dist-info/METADATA
whisperyt-0.1.4.dist-info/WHEEL
whisperyt-0.1.4.dist-info/top_level.txt
whisperyt-0.1.4.dist-info/RECORD
